[
  {
    "Name": "ubuntu-latest_Nginx1.23.4",
    "PackageRequirement": true,
    "RunPerformance": true,
    "NginxVersion": "1.23.4",
    "Image": "ubuntu-latest",
    "FullTests": true
  },
  {
    "MemCheck": true,
    "Image": "ubuntu-latest",
    "NginxVersion": "1.23.4",
    "Name": "ubuntu-latest_Nginx1.23.4_MemCheck"
  },
  {
    "BuildMethod": "static",
    "MemCheck": true,
    "Image": "ubuntu-latest",
    "NginxVersion": "1.23.4",
    "Name": "ubuntu-latest_Nginx1.23.4_MemCheck_Static"
  },
  {
    "Name": "ubuntu-latest_Nginx1.23.2",
    "PackageRequirement": true,
    "RunPerformance": false,
    "NginxVersion": "1.23.2",
    "Image": "ubuntu-latest",
    "FullTests": false
  },
  {
    "Name": "ubuntu-latest_Nginx1.21.6",
    "PackageRequirement": true,
    "RunPerformance": false,
    "NginxVersion": "1.21.6",
    "Image": "ubuntu-latest",
    "FullTests": false
  },
  {
    "Name": "ubuntu-latest_Nginx1.21.5",
    "PackageRequirement": true,
    "RunPerformance": false,
    "NginxVersion": "1.21.5",
    "Image": "ubuntu-latest",
    "FullTests": false
  },
  {
    "Name": "ubuntu-latest_Nginx1.21.3",
    "PackageRequirement": true,
    "RunPerformance": false,
    "NginxVersion": "1.21.3",
    "Image": "ubuntu-latest",
    "FullTests": false
  }
]
